{"cameraMode":{"drawMode":0,"name":"Shaded","section":"Shading Mode"},"sceneLighting":true,"audioPlay":false,"sceneViewState":{"m_AlwaysRefresh":false,"showFog":true,"showSkybox":true,"showFlares":true,"showImageEffects":true,"showParticleSystems":true,"showVisualEffectGraphs":true,"m_FxEnabled":true},"in2DMode":false,"pivot":{"x":0.0,"y":0.0,"z":10.0},"rotation":{"x":-0.060776982456445697,"y":0.9313409328460693,"z":-0.3087545931339264,"w":-0.18341907858848573},"size":4.789916515350342,"orthographic":false}